pyra_pytorch/__init__.py
pyra_pytorch/pyra_pytorch.py
pyra_pytorch-1.3.0.dist-info/LICENSE
pyra_pytorch-1.3.0.dist-info/METADATA
pyra_pytorch-1.3.0.dist-info/WHEEL
pyra_pytorch-1.3.0.dist-info/top_level.txt
pyra_pytorch-1.3.0.dist-info/RECORD
