Metadata-Version: 2.1
Name: pyra-pytorch
Version: 1.3.0
Summary: Pyramid Focus Augmentation: Medical Image Segmentation with Step Wise Focus
Home-page: https://github.com/vlbthambawita/pyra-pytorch
Author: Vajira Thambawita
Author-email: vlbthambawita@gmail.com
License: UNKNOWN
Platform: UNKNOWN
Classifier: Programming Language :: Python :: 3
Classifier: License :: OSI Approved :: MIT License
Classifier: Operating System :: OS Independent
Requires-Python: >=3.6
Requires-Dist: numpy
Requires-Dist: Pillow
